orca/__init__.py
orca/orca.py
orca/utils/__init__.py
orca/utils/logutil.py
orca/utils/testing.py
orca/utils/utils.py
orca-1.8.dist-info/LICENSE.txt
orca-1.8.dist-info/METADATA
orca-1.8.dist-info/WHEEL
orca-1.8.dist-info/top_level.txt
orca-1.8.dist-info/RECORD
