Metadata-Version: 2.1
Name: orca
Version: 1.8
Summary: Python library for task orchestration
Home-page: https://github.com/udst/orca
Author: UrbanSim Inc.
Author-email: info@urbansim.com
License: BSD
Classifier: Programming Language :: Python :: 2.7
Classifier: Programming Language :: Python :: 3
Classifier: Programming Language :: Python :: 3.5
Classifier: Programming Language :: Python :: 3.6
Classifier: Programming Language :: Python :: 3.7
Classifier: Programming Language :: Python :: 3.8
Classifier: Programming Language :: Python :: 3.9
Classifier: Programming Language :: Python :: 3.10
Classifier: License :: OSI Approved :: BSD License
License-File: LICENSE.txt
